[
  {
    "variation": "default",
    "name": "Default",
    "slice_type": "image_and_text",
    "items": [],
    "primary": {
      "imageSide": "Right",
      "image": {
        "dimensions": {
          "width": 900,
          "height": 500
        },
        "alt": "Placeholder image",
        "copyright": null,
        "url": "https://images.unsplash.com/photo-1448932223592-d1fc686e76ea?w=900&h=500&fit=crop"
      },
      "tagline": [
        {
          "type": "paragraph",
          "text": "Pariatur deserunt aute officia qui amet duis. Cupidatat excepteur esse ad fugiat esse fugiat consequat id. Laboris enim officia veniam deserunt do eiusmod nulla id sint consequat duis nisi nulla.",
          "spans": []
        }
      ],
      "text": [
        {
          "type": "heading1",
          "text": "Incubate world-class e-commerce",
          "spans": []
        },
        {
          "type": "paragraph",
          "text": "Elit eiusmod sint esse ipsum excepteur. Esse excepteur Lorem fugiat cupidatat occaecat adipisicing aute do aute ullamco occaecat commodo id et. Esse nisi enim enim excepteur consectetur nulla commodo cillum esse.",
          "spans": []
        }
      ],
      "buttonLink": {
        "link_type": "Web",
        "url": "https://prismic.io"
      },
      "buttonText": "expedite plug-and-play partnerships"
    }
  }
]